commander/__init__.py
commander/apps.py
commander/commands.py
commander/forms.py
commander/protection.py
commander/tests.py
commander/urls.py
commander/views.py
commander/management/commands/setrandompassword.py
commander/templates/command_details.html
commander/templates/command_list.html
django_commander-0.1.1.dist-info/METADATA
django_commander-0.1.1.dist-info/WHEEL
django_commander-0.1.1.dist-info/top_level.txt
django_commander-0.1.1.dist-info/RECORD
