Metadata-Version: 2.1
Name: django-commander
Version: 0.1.1
Summary: Run Django manage.py commands from the web
Home-page: https://github.com/vtbassmatt/django-commander
Author: Matt Cooper
Author-email: vtbassmatt@gmail.com
License: UNKNOWN
Platform: UNKNOWN
Classifier: Development Status :: 3 - Alpha
Classifier: Environment :: Web Environment
Classifier: Intended Audience :: Developers
Classifier: License :: OSI Approved :: MIT License
Classifier: Programming Language :: Python :: 3
